{
  "signals": {
    "mocs-ready": {
      "at": "2026-03-03T17:32:45.782Z",
      "emittedBy": "finding-pipeline",
      "newMocs": 0
    },
    "fixes-applied": {
      "at": "2026-03-03T17:32:47.542Z",
      "emittedBy": "fix-engine",
      "applied": 0,
      "failed": 0
    },
    "intelligence-complete": {
      "at": "2026-03-03T17:33:07.546Z",
      "emittedBy": "intelligence",
      "subsystems": 36,
      "failed": 2
    },
    "diagnostics-complete": {
      "at": "2026-03-03T17:33:52.992Z",
      "emittedBy": "diagnostics",
      "actions": 5,
      "healthChecks": 8,
      "healthChecksFailing": 1
    },
    "diagnostics-requested": {
      "at": "2026-03-03T17:32:47.636Z",
      "emittedBy": "convergence-tracker",
      "reason": "stuck",
      "mocCount": 3
    },
    "docs-synced": {
      "at": "2026-03-03T17:08:46.872Z",
      "emittedBy": "docs-sync",
      "driftCount": 1,
      "fixedCount": 1
    },
    "daemon-started": {
      "timestamp": "2026-03-03T15:13:09.424Z",
      "at": "2026-03-03T15:13:09.424Z",
      "from": "daemon",
      "pid": 76504
    },
    "build-complete": {
      "at": "2026-03-03T17:32:17.300Z",
      "emittedBy": "builder",
      "iteration": 372,
      "specCompletionRate": 0,
      "complianceScore": 0.7,
      "phase": "polish",
      "gapsRemaining": 10,
      "mocsCreated": 3,
      "scaffolded": 0
    },
    "tests-regenerated": {
      "at": "2026-03-03T17:37:09.584Z",
      "emittedBy": "builder",
      "feature": "database_schema",
      "routes": []
    },
    "tests-complete": {
      "at": "2026-03-03T17:32:41.429Z",
      "emittedBy": "test-runner",
      "iteration": 362,
      "passed": 10,
      "failed": 0,
      "total": 10,
      "playwrightExitOk": true
    },
    "circuit-broken": {
      "at": "2026-03-03T17:33:22.941Z",
      "emittedBy": "diagnostics",
      "claw": "diagnostics",
      "reason": "5 consecutive failures (same error x5)",
      "consecutiveFailures": 5
    },
    "claw-crashed": {
      "at": "2026-03-03T15:44:41.363Z",
      "emittedBy": "daemon",
      "claw": "builder",
      "reason": "exceeded max restarts (4/hour) — healing mode"
    }
  },
  "claws": {
    "builder": {
      "status": "running",
      "pid": 73700,
      "lastRun": "2026-03-03T17:32:17.303Z",
      "nextRun": "2026-03-03T19:32:17.303Z",
      "heartbeat": "2026-03-03T17:32:47.325Z",
      "cycle": 373,
      "phase": "starting",
      "lastCycleDurationMs": 99061,
      "lastCycleResult": "ok",
      "lastError": "exceeded max restarts — in healing mode (5min backoff)"
    },
    "cp-meta": {
      "status": "idle",
      "pid": 73192,
      "lastRun": "2026-03-03T17:32:49.372Z",
      "nextRun": "2026-03-03T18:02:49.372Z",
      "heartbeat": "2026-03-03T17:36:14.593Z",
      "cycle": 478,
      "phase": "starting",
      "lastCycleDurationMs": 16648,
      "lastCycleResult": "error"
    },
    "finding-pipeline": {
      "status": "idle",
      "pid": 93448,
      "lastRun": "2026-03-03T17:32:45.891Z",
      "nextRun": "2026-03-03T18:02:45.891Z",
      "heartbeat": "2026-03-03T17:36:14.310Z",
      "cycle": 361,
      "phase": "starting",
      "lastCycleDurationMs": 767,
      "lastCycleResult": "ok"
    },
    "diagnostics": {
      "status": "idle",
      "pid": 48148,
      "lastRun": "2026-03-03T17:33:52.994Z",
      "nextRun": "2026-03-03T23:33:52.994Z",
      "heartbeat": "2026-03-03T17:36:14.421Z",
      "cycle": 557,
      "phase": "starting",
      "lastCycleDurationMs": 24,
      "lastCycleResult": "error"
    },
    "fix-engine": {
      "status": "idle",
      "pid": 52944,
      "lastRun": "2026-03-03T17:32:47.657Z",
      "nextRun": "2026-03-03T18:32:47.657Z",
      "heartbeat": "2026-03-03T17:36:15.049Z",
      "cycle": 140,
      "phase": "docs-update",
      "lastCycleDurationMs": 1176,
      "lastCycleResult": "ok"
    },
    "intelligence": {
      "status": "idle",
      "pid": 80784,
      "lastRun": "2026-03-03T17:33:07.549Z",
      "nextRun": "2026-03-03T19:33:07.549Z",
      "heartbeat": "2026-03-03T17:37:07.586Z",
      "cycle": 521,
      "phase": "starting",
      "lastCycleDurationMs": 11566,
      "lastCycleResult": "ok"
    },
    "test-runner": {
      "status": "idle",
      "pid": 81784,
      "lastRun": "2026-03-03T17:32:41.432Z",
      "nextRun": "2026-03-04T01:32:41.432Z",
      "heartbeat": "2026-03-03T17:36:14.688Z",
      "cycle": 362,
      "phase": "starting",
      "lastCycleDurationMs": 6809,
      "lastCycleResult": "ok"
    },
    "health-deploy": {
      "status": "idle",
      "pid": 32696,
      "lastRun": "2026-03-03T17:33:21.188Z",
      "nextRun": "2026-03-03T21:33:21.188Z",
      "heartbeat": "2026-03-03T17:36:17.795Z",
      "cycle": 519,
      "phase": "starting",
      "lastCycleDurationMs": 2802,
      "lastCycleResult": "error"
    },
    "observer": {
      "status": "idle",
      "pid": 32692,
      "lastRun": "2026-03-03T17:09:02.548Z",
      "nextRun": "2026-03-03T18:09:02.548Z",
      "heartbeat": "2026-03-03T17:36:14.515Z",
      "cycle": 16,
      "phase": "starting",
      "lastCycleDurationMs": 222,
      "lastCycleResult": "ok"
    },
    "test-regen": {
      "status": "idle",
      "pid": 85240,
      "lastRun": "2026-03-03T17:08:47.259Z",
      "nextRun": "2026-03-03T18:08:47.259Z",
      "heartbeat": "2026-03-03T17:36:14.562Z",
      "cycle": 16,
      "phase": "starting",
      "lastCycleDurationMs": 1,
      "lastCycleResult": "ok"
    },
    "docs-sync": {
      "status": "idle",
      "pid": 84852,
      "lastRun": "2026-03-03T17:08:46.876Z",
      "nextRun": "2026-03-03T18:08:46.876Z",
      "heartbeat": "2026-03-03T17:36:14.453Z",
      "cycle": 16,
      "phase": "starting",
      "lastCycleDurationMs": 13,
      "lastCycleResult": "ok"
    }
  }
}
