{
  "signals": {
    "mocs-ready": {
      "at": "2026-03-03T12:29:00.019Z",
      "emittedBy": "finding-pipeline",
      "newMocs": 0
    },
    "fixes-applied": {
      "at": "2026-03-03T12:29:20.606Z",
      "emittedBy": "fix-engine",
      "applied": 0,
      "failed": 0
    },
    "intelligence-complete": {
      "at": "2026-03-03T12:29:41.153Z",
      "emittedBy": "intelligence",
      "subsystems": 36,
      "failed": 2
    },
    "diagnostics-complete": {
      "at": "2026-03-03T12:29:33.714Z",
      "emittedBy": "diagnostics",
      "actions": 3,
      "healthChecks": 8,
      "healthChecksFailing": 1
    },
    "diagnostics-requested": {
      "at": "2026-03-03T12:29:20.696Z",
      "emittedBy": "convergence-tracker",
      "reason": "stuck",
      "mocCount": 2
    },
    "docs-synced": {
      "at": "2026-03-03T12:08:22.158Z",
      "emittedBy": "docs-sync",
      "driftCount": 1,
      "fixedCount": 1
    },
    "daemon-started": {
      "timestamp": "2026-03-03T04:41:34.371Z",
      "at": "2026-03-03T04:41:34.371Z",
      "from": "daemon",
      "pid": 60320
    },
    "build-complete": {
      "at": "2026-03-03T12:28:26.038Z",
      "emittedBy": "builder",
      "iteration": 255,
      "specCompletionRate": 0,
      "complianceScore": 0.206,
      "phase": "build",
      "gapsRemaining": 10,
      "mocsCreated": 3,
      "scaffolded": 1
    },
    "tests-regenerated": {
      "at": "2026-03-03T12:28:25.888Z",
      "emittedBy": "builder",
      "feature": "authentication_and_user_management",
      "routes": [
        "/auth/login",
        "/auth/signup"
      ]
    },
    "tests-complete": {
      "at": "2026-03-03T12:28:47.783Z",
      "emittedBy": "test-runner",
      "iteration": 251,
      "passed": 10,
      "failed": 0,
      "total": 10,
      "playwrightExitOk": true
    },
    "circuit-broken": {
      "at": "2026-03-03T12:27:11.104Z",
      "emittedBy": "builder",
      "claw": "builder",
      "reason": "5 consecutive failures (same error x5)",
      "consecutiveFailures": 5
    }
  },
  "claws": {
    "builder": {
      "status": "running",
      "pid": 47052,
      "lastRun": "2026-03-03T12:28:26.041Z",
      "nextRun": "2026-03-03T14:28:26.041Z",
      "heartbeat": "2026-03-03T12:29:41.594Z",
      "cycle": 256,
      "phase": "starting",
      "lastCycleDurationMs": 44910,
      "lastCycleResult": "error"
    },
    "cp-meta": {
      "status": "idle",
      "pid": 61764,
      "lastRun": "2026-03-03T12:29:30.257Z",
      "nextRun": "2026-03-03T12:59:30.257Z",
      "heartbeat": "2026-03-03T12:29:41.450Z",
      "cycle": 312,
      "phase": "starting",
      "lastCycleDurationMs": 49257,
      "lastCycleResult": "error"
    },
    "finding-pipeline": {
      "status": "idle",
      "pid": 26408,
      "lastRun": "2026-03-03T12:29:00.115Z",
      "nextRun": "2026-03-03T12:59:00.115Z",
      "heartbeat": "2026-03-03T12:29:41.257Z",
      "cycle": 251,
      "phase": "starting",
      "lastCycleDurationMs": 718,
      "lastCycleResult": "ok"
    },
    "diagnostics": {
      "status": "idle",
      "pid": 94912,
      "lastRun": "2026-03-03T12:29:33.716Z",
      "nextRun": "2026-03-03T18:29:33.716Z",
      "heartbeat": "2026-03-03T12:29:41.370Z",
      "cycle": 378,
      "phase": "starting",
      "lastCycleDurationMs": 16,
      "lastCycleResult": "error"
    },
    "fix-engine": {
      "status": "idle",
      "pid": 53928,
      "lastRun": "2026-03-03T12:29:20.718Z",
      "nextRun": "2026-03-03T13:29:20.718Z",
      "heartbeat": "2026-03-03T12:29:46.452Z",
      "cycle": 475,
      "phase": "docs-update",
      "lastCycleDurationMs": 2189,
      "lastCycleResult": "ok"
    },
    "intelligence": {
      "status": "idle",
      "pid": 37012,
      "lastRun": "2026-03-03T12:29:41.156Z",
      "nextRun": "2026-03-03T14:29:41.156Z",
      "heartbeat": "2026-03-03T12:29:41.158Z",
      "cycle": 360,
      "phase": "starting",
      "lastCycleDurationMs": 9688,
      "lastCycleResult": "ok"
    },
    "test-runner": {
      "status": "idle",
      "pid": 59396,
      "lastRun": "2026-03-03T12:28:47.785Z",
      "nextRun": "2026-03-03T20:28:47.785Z",
      "heartbeat": "2026-03-03T12:29:41.642Z",
      "cycle": 251,
      "phase": "starting",
      "lastCycleDurationMs": 6497,
      "lastCycleResult": "ok"
    },
    "health-deploy": {
      "status": "running",
      "pid": 31608,
      "lastRun": "2026-03-03T12:28:07.418Z",
      "nextRun": "2026-03-03T16:28:07.418Z",
      "heartbeat": "2026-03-03T12:29:52.501Z",
      "cycle": 359,
      "phase": "starting",
      "lastCycleDurationMs": 3141,
      "lastCycleResult": "error"
    },
    "observer": {
      "status": "idle",
      "pid": 39628,
      "lastRun": "2026-03-03T12:08:24.203Z",
      "nextRun": "2026-03-03T13:08:24.203Z",
      "heartbeat": "2026-03-03T12:29:41.242Z",
      "cycle": 11,
      "phase": "starting",
      "lastCycleDurationMs": 219,
      "lastCycleResult": "ok"
    },
    "test-regen": {
      "status": "idle",
      "pid": 6344,
      "lastRun": "2026-03-03T12:08:21.865Z",
      "nextRun": "2026-03-03T13:08:21.865Z",
      "heartbeat": "2026-03-03T12:29:41.306Z",
      "cycle": 11,
      "phase": "starting",
      "lastCycleDurationMs": 1,
      "lastCycleResult": "ok"
    },
    "docs-sync": {
      "status": "idle",
      "pid": 7124,
      "lastRun": "2026-03-03T12:08:22.163Z",
      "nextRun": "2026-03-03T13:08:22.163Z",
      "heartbeat": "2026-03-03T12:29:41.322Z",
      "cycle": 11,
      "phase": "starting",
      "lastCycleDurationMs": 11,
      "lastCycleResult": "ok"
    }
  }
}
