{
  "signals": {
    "mocs-ready": {
      "at": "2026-03-03T19:52:35.860Z",
      "emittedBy": "finding-pipeline",
      "newMocs": 0
    },
    "fixes-applied": {
      "at": "2026-03-03T19:52:15.794Z",
      "emittedBy": "fix-engine",
      "applied": 0,
      "failed": 0
    },
    "intelligence-complete": {
      "at": "2026-03-03T19:52:29.293Z",
      "emittedBy": "intelligence",
      "subsystems": 36,
      "failed": 2
    },
    "diagnostics-complete": {
      "at": "2026-03-03T19:51:38.741Z",
      "emittedBy": "diagnostics",
      "actions": 3,
      "healthChecks": 8,
      "healthChecksFailing": 1
    },
    "diagnostics-requested": {
      "at": "2026-03-03T19:32:29.950Z",
      "emittedBy": "convergence-tracker",
      "reason": "stuck",
      "mocCount": 3
    },
    "docs-synced": {
      "at": "2026-03-03T19:08:50.685Z",
      "emittedBy": "docs-sync",
      "driftCount": 1,
      "fixedCount": 1
    },
    "daemon-started": {
      "timestamp": "2026-03-03T19:39:46.099Z",
      "at": "2026-03-03T19:39:46.099Z",
      "from": "daemon",
      "pid": 88916
    },
    "build-complete": {
      "at": "2026-03-03T19:52:38.001Z",
      "emittedBy": "builder",
      "iteration": 467,
      "specCompletionRate": 1,
      "gapsRemaining": 0
    },
    "tests-regenerated": {
      "at": "2026-03-03T19:34:26.909Z",
      "emittedBy": "builder",
      "feature": "authentication_and_user_management",
      "routes": [
        "/auth/login",
        "/auth/signup"
      ]
    },
    "tests-complete": {
      "at": "2026-03-03T19:52:18.246Z",
      "emittedBy": "test-runner",
      "iteration": 456,
      "passed": 10,
      "failed": 0,
      "total": 10,
      "playwrightExitOk": true
    },
    "circuit-broken": {
      "at": "2026-03-03T19:52:44.502Z",
      "emittedBy": "health-deploy",
      "claw": "health-deploy",
      "reason": "5 consecutive failures (same error x5)",
      "consecutiveFailures": 5
    }
  },
  "claws": {
    "builder": {
      "status": "idle",
      "pid": 89512,
      "lastRun": "2026-03-03T19:52:38.003Z",
      "nextRun": "2026-03-04T01:52:38.003Z",
      "heartbeat": "2026-03-03T19:52:38.006Z",
      "cycle": 467,
      "phase": "starting",
      "lastCycleDurationMs": 100,
      "lastCycleResult": "ok",
      "lastError": "exceeded max restarts — in healing mode (5min backoff)"
    },
    "cp-meta": {
      "status": "idle",
      "pid": 43432,
      "lastRun": "2026-03-03T19:52:43.124Z",
      "nextRun": "2026-03-03T20:22:43.124Z",
      "heartbeat": "2026-03-03T19:52:43.126Z",
      "cycle": 645,
      "phase": "starting",
      "lastCycleDurationMs": 6596,
      "lastCycleResult": "error"
    },
    "finding-pipeline": {
      "status": "idle",
      "pid": 54016,
      "lastRun": "2026-03-03T19:52:35.955Z",
      "nextRun": "2026-03-03T20:22:35.955Z",
      "heartbeat": "2026-03-03T19:52:35.958Z",
      "cycle": 456,
      "phase": "starting",
      "lastCycleDurationMs": 705,
      "lastCycleResult": "ok"
    },
    "diagnostics": {
      "status": "idle",
      "pid": 17280,
      "lastRun": "2026-03-03T19:51:38.743Z",
      "nextRun": "2026-03-04T01:51:38.743Z",
      "heartbeat": "2026-03-03T19:51:50.209Z",
      "cycle": 633,
      "phase": "starting",
      "lastCycleDurationMs": 20,
      "lastCycleResult": "error"
    },
    "fix-engine": {
      "status": "running",
      "pid": 10636,
      "lastRun": "2026-03-03T19:52:15.897Z",
      "nextRun": "2026-03-03T20:52:15.897Z",
      "heartbeat": "2026-03-03T19:52:45.920Z",
      "cycle": 250,
      "phase": "docs-update",
      "lastCycleDurationMs": 1334,
      "lastCycleResult": "ok"
    },
    "intelligence": {
      "status": "idle",
      "pid": 94116,
      "lastRun": "2026-03-03T19:52:29.296Z",
      "nextRun": "2026-03-03T21:52:29.296Z",
      "heartbeat": "2026-03-03T19:52:36.984Z",
      "cycle": 611,
      "phase": "starting",
      "lastCycleDurationMs": 10350,
      "lastCycleResult": "ok"
    },
    "test-runner": {
      "status": "idle",
      "pid": 29200,
      "lastRun": "2026-03-03T19:52:18.248Z",
      "nextRun": "2026-03-04T03:52:18.248Z",
      "heartbeat": "2026-03-03T19:52:18.251Z",
      "cycle": 456,
      "phase": "starting",
      "lastCycleDurationMs": 6527,
      "lastCycleResult": "ok"
    },
    "health-deploy": {
      "status": "idle",
      "pid": 39532,
      "lastRun": "2026-03-03T19:52:44.497Z",
      "nextRun": "2026-03-03T23:52:44.497Z",
      "heartbeat": "2026-03-03T19:52:44.506Z",
      "cycle": 609,
      "phase": "starting",
      "lastCycleDurationMs": 3870,
      "lastCycleResult": "error"
    },
    "observer": {
      "status": "idle",
      "pid": 94528,
      "lastRun": "2026-03-03T19:09:06.850Z",
      "nextRun": "2026-03-03T20:09:06.850Z",
      "heartbeat": "2026-03-03T19:51:50.099Z",
      "cycle": 18,
      "phase": "starting",
      "lastCycleDurationMs": 333,
      "lastCycleResult": "ok"
    },
    "test-regen": {
      "status": "idle",
      "pid": 75500,
      "lastRun": "2026-03-03T19:08:50.911Z",
      "nextRun": "2026-03-03T20:08:50.911Z",
      "heartbeat": "2026-03-03T19:51:50.225Z",
      "cycle": 18,
      "phase": "starting",
      "lastCycleDurationMs": 1,
      "lastCycleResult": "ok"
    },
    "docs-sync": {
      "status": "idle",
      "pid": 21308,
      "lastRun": "2026-03-03T19:08:50.690Z",
      "nextRun": "2026-03-03T20:08:50.690Z",
      "heartbeat": "2026-03-03T19:51:50.177Z",
      "cycle": 18,
      "phase": "starting",
      "lastCycleDurationMs": 17,
      "lastCycleResult": "ok"
    }
  }
}
