{
  "passed": [
    "moc-queue: correct format ({ mocs: [...] }), 67 entries",
    "findings: valid format, 0 entries",
    "claw-signals: correct format ({ signals, claws })",
    "issue-queue: all 67 entries have valid schema",
    "findings: all 0 entries have valid schema",
    "convergence: valid state \"converged\"",
    "plausibility: health summary queue depth consistent with moc-queue",
    "config-alignment: auto-tune made 2 adjustments in 24h (within bounds)"
  ],
  "failed": [],
  "warnings": [
    "config-alignment: test-runner.coverageBasedSuspend is not set in config (defaults to false). Add it explicitly to prevent surprises.",
    "signal-flow: test-runner ran recently but no tests-complete signal found.",
    "principles: daemon-principles.json does not exist — no design constraints encoded"
  ],
  "at": "2026-03-03T04:41:53.753Z",
  "passedCount": 8,
  "failedCount": 0,
  "warningCount": 3,
  "healthy": true
}
